{
  "title": "Senior Android Engineer (Remote)",
  "company": "Nimbus Labs",
  "location": "Remote, Europe",
  "url": "https://example.com/jobs/senior-android-engineer",
  "source": "linkedin",
  "description": "Nimbus Labs is a remote-first product company building a consumer mobile platform used by millions. We are hiring a Senior Android Engineer to join our fully distributed engineering team (working language: English).\n\nWhat you'll do:\n- Build and maintain our Android application in Kotlin and Java\n- Collaborate on architecture for offline-first, real-time features\n- Integrate with IoT/Bluetooth hardware and our backend APIs\n- Mentor mid-level engineers and drive code quality in an Agile team\n\nWhat we're looking for:\n- 4+ years of professional Android development (Kotlin and/or Java)\n- Solid CS fundamentals: algorithms, concurrency, software architecture\n- Experience integrating with hardware (BLE, embedded devices) is a strong plus\n- Comfortable in a fully remote, asynchronous environment\n\nNice to have:\n- C++ for native modules\n- Experience with automation/CI\n- Security-minded development\n\nCompensation: 3,500 - 4,500 EUR/month net, depending on experience. Fully remote (work from anywhere in Europe). Contractor (B2B) or employment both possible."
}
